customoauth/__init__.py
customoauth/customoauth.py
jmorman_authenticator-0.0.20.dist-info/LICENSE
jmorman_authenticator-0.0.20.dist-info/METADATA
jmorman_authenticator-0.0.20.dist-info/WHEEL
jmorman_authenticator-0.0.20.dist-info/top_level.txt
jmorman_authenticator-0.0.20.dist-info/RECORD
