Metadata-Version: 2.1
Name: jmorman-authenticator
Version: 0.0.20
Summary: Custom authenticator
Home-page: UNKNOWN
Author: John Morman
Author-email: jmorman@microsoft.com
License: 3 Clause BSD
Platform: UNKNOWN
Requires-Dist: oauthenticator
